fastapi_vers.py
fastapi_vers-0.3.0.dist-info/LICENSE
fastapi_vers-0.3.0.dist-info/METADATA
fastapi_vers-0.3.0.dist-info/WHEEL
fastapi_vers-0.3.0.dist-info/top_level.txt
fastapi_vers-0.3.0.dist-info/RECORD
