Metadata-Version: 2.1
Name: fastapi-vers
Version: 0.3.0
Summary: FastAPI versioning
Author: Roma Koshel
Author-email: roma.koshel@gmail.com
License: MIT
Classifier: Development Status :: 2 - Pre-Alpha
Classifier: Programming Language :: Python
Classifier: Programming Language :: Python :: 3
Classifier: Operating System :: POSIX :: Linux
Classifier: Operating System :: MacOS :: MacOS X
Requires-Python: >=3.8
License-File: LICENSE
Requires-Dist: fastapi (>=0.62.0)
Requires-Dist: packaging
